Metadata-Version: 2.1
Name: wis-s3api
Version: 0.0.11
Summary: minio/s3 api
Home-page: https://github.com/zjf014/wis-s3api
Author: Jianfeng Zhu
Author-email: zjf014@gmail.com
License: MIT license
Keywords: wis_s3api
Classifier: Development Status :: 2 - Pre-Alpha
Classifier: Intended Audience :: Developers
Classifier: License :: OSI Approved :: MIT License
Classifier: Natural Language :: English
Classifier: Programming Language :: Python :: 3
Classifier: Programming Language :: Python :: 3.7
Classifier: Programming Language :: Python :: 3.8
Classifier: Programming Language :: Python :: 3.9
Classifier: Programming Language :: Python :: 3.10
Requires-Python: >=3.7
License-File: LICENSE
